json_wrapper.py
PyJsonWrapper-0.0.1.dist-info/LICENSE
PyJsonWrapper-0.0.1.dist-info/METADATA
PyJsonWrapper-0.0.1.dist-info/WHEEL
PyJsonWrapper-0.0.1.dist-info/top_level.txt
PyJsonWrapper-0.0.1.dist-info/RECORD
