Metadata-Version: 2.1
Name: PyJsonWrapper
Version: 0.0.1
Summary: Some useful tools for python
Author-email: cn_qlg <cn_qlg@163.com>
License: MIT License
Project-URL: Homepage, https://github.com/cn-qlg/PyJsonWrapper
Project-URL: Bug Tracker, https://github.com/cn-qlg/PyJsonWrapper/issues
Classifier: Programming Language :: Python :: 3
Classifier: License :: OSI Approved :: MIT License
Classifier: Operating System :: OS Independent
Requires-Python: >=3.9
License-File: LICENSE
